photos_drive/__init__.py
photos_drive/backup/backup_photos.py
photos_drive/backup/diffs.py
photos_drive/backup/diffs_assignments.py
photos_drive/backup/gphotos_uploader.py
photos_drive/backup/processed_diffs.py
photos_drive/clean/clean_system.py
photos_drive/cli/app.py
photos_drive/cli/commands/add.py
photos_drive/cli/commands/clean.py
photos_drive/cli/commands/config/__init__.py
photos_drive/cli/commands/config/add.py
photos_drive/cli/commands/config/init.py
photos_drive/cli/commands/config/reauthorize.py
photos_drive/cli/commands/config/view.py
photos_drive/cli/commands/db/__init__.py
photos_drive/cli/commands/db/delete_child_album_ids_from_albums_db.py
photos_drive/cli/commands/db/delete_media_item_ids_from_albums_db.py
photos_drive/cli/commands/db/delete_media_items_without_album_id.py
photos_drive/cli/commands/db/dump.py
photos_drive/cli/commands/db/generate_embeddings.py
photos_drive/cli/commands/db/initialize_map_cells_db.py
photos_drive/cli/commands/db/restore.py
photos_drive/cli/commands/db/set_media_item_date_taken_fields.py
photos_drive/cli/commands/db/set_media_item_width_height_fields.py
photos_drive/cli/commands/delete.py
photos_drive/cli/commands/llm.py
photos_drive/cli/commands/llms/tools/find_photos.py
photos_drive/cli/commands/llms/tools/find_similar_photos.py
photos_drive/cli/commands/llms/tools/media_item.py
photos_drive/cli/commands/llms/tools/search_photos_by_text.py
photos_drive/cli/commands/llms/trial_4.py
photos_drive/cli/commands/llms/utils/CombinedMemory.py
photos_drive/cli/commands/llms/utils/pil_image_to_base64.py
photos_drive/cli/commands/sync.py
photos_drive/cli/commands/teardown.py
photos_drive/cli/commands/usage.py
photos_drive/cli/shared/config.py
photos_drive/cli/shared/files.py
photos_drive/cli/shared/inputs.py
photos_drive/cli/shared/logging.py
photos_drive/cli/shared/printer.py
photos_drive/cli/shared/typer.py
photos_drive/diff/get_diffs.py
photos_drive/py.typed
photos_drive/shared/blob_store/gphotos/albums.py
photos_drive-8.2.7.dist-info/METADATA
photos_drive-8.2.7.dist-info/WHEEL
photos_drive-8.2.7.dist-info/entry_points.txt
photos_drive-8.2.7.dist-info/RECORD
