Metadata-Version: 2.3
Name: photos_drive
Version: 8.2.7
Summary: 
Author: Emilio Kartono
Author-email: e.kartonoe@gmail.com
Requires-Python: >=3.10,<3.13
Classifier: Programming Language :: Python :: 3
Classifier: Programming Language :: Python :: 3.10
Classifier: Programming Language :: Python :: 3.11
Classifier: Programming Language :: Python :: 3.12
Requires-Dist: backoff (>=2.2.1,<3.0.0)
Requires-Dist: dacite (>=1.8.1,<2.0.0)
Requires-Dist: event-bus (>=1.0.2,<2.0.0)
Requires-Dist: exifread (>=3.0.0,<4.0.0)
Requires-Dist: faiss-cpu (>=1.11.0.post1,<2.0.0)
Requires-Dist: google-api-python-client (>=2.156.0,<3.0.0)
Requires-Dist: google-auth-oauthlib (>=1.2.1,<2.0.0)
Requires-Dist: h3 (>=4.3.0,<5.0.0)
Requires-Dist: langchain (>=0.3.26,<0.4.0)
Requires-Dist: langchain-community (>=0.3.27,<0.4.0)
Requires-Dist: langchain-experimental (>=0.3.4,<0.4.0)
Requires-Dist: langchain-google-genai (>=2.1.8,<3.0.0)
Requires-Dist: langchain-google-vertexai (>=2.0.27,<3.0.0)
Requires-Dist: langgraph (>=0.5.4,<0.6.0)
Requires-Dist: langmem (>=0.0.28,<0.0.29)
Requires-Dist: numpy (<2)
Requires-Dist: open-clip-torch (>=2.32.0,<3.0.0)
Requires-Dist: opencv-python-headless (>=4.11.0.86,<5.0.0.0)
Requires-Dist: pillow (>=11.2.1,<12.0.0)
Requires-Dist: pillow-heif (>=0.22.0,<0.23.0)
Requires-Dist: prettytable (>=3.12.0,<4.0.0)
Requires-Dist: pydantic (>=2.11.7,<3.0.0)
Requires-Dist: pyexiftool (>=0.5.6,<0.6.0)
Requires-Dist: pymongo (<4.11)
Requires-Dist: python-magic (>=0.4.27,<0.5.0)
Requires-Dist: rich (>=14.0.0,<15.0.0)
Requires-Dist: termcolor (>=2.5.0,<3.0.0)
Requires-Dist: torch (<=2.2.2)
Requires-Dist: tqdm (>=4.67.1,<5.0.0)
Requires-Dist: transformers (>=4.53.2,<5.0.0)
Requires-Dist: typer (>=0.15.1,<0.16.0)
Requires-Dist: types-exifread (>=3.0.0.20240806,<4.0.0.0)
Requires-Dist: types-requests (>=2.32.0.20241016,<3.0.0.0)
Requires-Dist: typing-extensions (>=4.14.1,<5.0.0)
Requires-Dist: xxhash (>=3.5.0,<4.0.0)
